trzsz_iterm2-1.1.5-py3.11-nspkg.pth
iterm2-tests/__init__.py
iterm2-tests/test_text_progress.py
iterm2-tests/trzsz/__init__.py
iterm2-tests/trzsz/iterm2/__init__.py
iterm2-tests/trzsz/iterm2/__version__.py
iterm2-tests/trzsz/iterm2/main.py
iterm2-tests/trzsz/iterm2/text_progress.py
iterm2-tests/trzsz/iterm2/zenity_progress.py
trzsz/iterm2/__init__.py
trzsz/iterm2/__version__.py
trzsz/iterm2/main.py
trzsz/iterm2/text_progress.py
trzsz/iterm2/zenity_progress.py
trzsz_iterm2-1.1.5.dist-info/METADATA
trzsz_iterm2-1.1.5.dist-info/WHEEL
trzsz_iterm2-1.1.5.dist-info/entry_points.txt
trzsz_iterm2-1.1.5.dist-info/namespace_packages.txt
trzsz_iterm2-1.1.5.dist-info/top_level.txt
trzsz_iterm2-1.1.5.dist-info/RECORD
